chantilly/__init__.py
chantilly/__version__.py
chantilly/adjectives.txt
chantilly/api.py
chantilly/cli.py
chantilly/dashboard.py
chantilly/exceptions.py
chantilly/flavors.py
chantilly/food_names.txt
chantilly/storage.py
chantilly/static/favicon.ico
chantilly/static/logo.svg
chantilly/static/style.css
chantilly/templates/index.html
tests/__init__.py
tests/conftest.py
tests/test_api.py
tests/test_cli.py
tests/test_factory.py
tests/test_scenarios.py
chantilly-0.2.0.dist-info/LICENSE
chantilly-0.2.0.dist-info/METADATA
chantilly-0.2.0.dist-info/WHEEL
chantilly-0.2.0.dist-info/entry_points.txt
chantilly-0.2.0.dist-info/top_level.txt
chantilly-0.2.0.dist-info/RECORD
