Metadata-Version: 2.1
Name: chantilly
Version: 0.2.0
Summary: Deployment tool for online machine learning models
Home-page: https://github.com/creme-ml/chantilly
Author: Max Halford
Author-email: maxhalford25@gmail.com
License: BSD-3
Platform: UNKNOWN
Classifier: License :: OSI Approved :: BSD License
Classifier: Programming Language :: Python
Classifier: Programming Language :: Python :: 3
Classifier: Programming Language :: Python :: 3.7
Classifier: Programming Language :: Python :: 3.8
Classifier: Programming Language :: Python :: Implementation :: CPython
Classifier: Programming Language :: Python :: Implementation :: PyPy
Requires-Python: >=3.7.0
Requires-Dist: creme (>=0.5.0)
Requires-Dist: dill (>=0.3.1.1)
Requires-Dist: Flask (>=1.1.1)
Requires-Dist: marshmallow (>=3.5.1)
Provides-Extra: dev
Requires-Dist: flake8 (>=3.7.9) ; extra == 'dev'
Requires-Dist: mypy (>=0.770) ; extra == 'dev'
Requires-Dist: pytest (>=5.3.5) ; extra == 'dev'
Requires-Dist: pytest-cov (>=2.8.1) ; extra == 'dev'
Provides-Extra: redis
Requires-Dist: redis (>=3.5) ; extra == 'redis'
